edc_rest/__init__.py
edc_rest/binary_field.py
edc_rest/serializers.py
edc_rest/settings.py
edc_rest/tests.py
edc_rest/urls.py
edc_rest/wsgi.py
edc_rest-0.1.3.dist-info/METADATA
edc_rest-0.1.3.dist-info/RECORD
edc_rest-0.1.3.dist-info/WHEEL
edc_rest-0.1.3.dist-info/top_level.txt
